<?xml version="1.0" encoding="UTF-8"?>

<!-- generated on 2023-03-31 16:34:10 by Eclipse SUMO sumo Version 1.12.0
<configuration xmlns:xsi="http://www.w3.org/2001/XMLSchema-instance" xsi:noNamespaceSchemaLocation="http://sumo.dlr.de/xsd/sumoConfiguration.xsd">

    <input>
        <net-file value="../../inputs/maps/small_dublin.net.xml"/>
        <route-files value="../../inputs/routes/small_dublin.rou.xml"/>
    </input>

    <output>
        <tripinfo-output value="../../outputs/trips/small_dublin_trip_62.xml"/>
        <vehroute-output value="../../outputs/vehroute/small_dublin_vr_62.xml"/>
    </output>

    <time>
        <begin value="0"/>
    </time>

    <processing>
        <threads value="12"/>
    </processing>

    <report>
        <verbose value="false"/>
        <no-warnings value="true"/>
        <no-step-log value="true"/>
    </report>

    <emissions>
        <device.emissions.probability value="1"/>
    </emissions>

    <traci_server>
        <remote-port value="54533"/>
    </traci_server>

</configuration>
-->

<tripinfos xmlns:xsi="http://www.w3.org/2001/XMLSchema-instance" xsi:noNamespaceSchemaLocation="http://sumo.dlr.de/xsd/tripinfo_file.xsd">
    <tripinfo id="3" depart="6.00" departLane="129211847#1_0" departPos="5.10" departSpeed="0.00" departDelay="0.00" arrival="85.00" arrivalLane="317101094#1_1" arrivalPos="10.29" arrivalSpeed="7.45" duration="79.00" routeLength="786.09" waitingTime="0.00" waitingCount="0" stopTime="0.00" timeLoss="11.15" rerouteNo="0" devices="vehroute_3 tripinfo_3 emissions_3" vType="DEFAULT_VEHTYPE" speedFactor="1.08" vaporized="">
        <emissions CO_abs="3085.059814" CO2_abs="187364.857545" HC_abs="18.412158" PMx_abs="3.193056" NOx_abs="75.832871" fuel_abs="80.540490" electricity_abs="0"/>
    </tripinfo>
    <tripinfo id="8" depart="16.00" departLane="-4287294#9_0" departPos="5.10" departSpeed="0.00" departDelay="0.00" arrival="86.00" arrivalLane="317544588#0_0" arrivalPos="26.18" arrivalSpeed="7.62" duration="70.00" routeLength="721.43" waitingTime="0.00" waitingCount="0" stopTime="0.00" timeLoss="7.53" rerouteNo="0" devices="vehroute_8 tripinfo_8 emissions_8" vType="DEFAULT_VEHTYPE" speedFactor="0.94" vaporized="">
        <emissions CO_abs="2218.552559" CO2_abs="143262.918998" HC_abs="13.419313" PMx_abs="2.260235" NOx_abs="56.768764" fuel_abs="61.583034" electricity_abs="0"/>
    </tripinfo>
    <tripinfo id="16" depart="32.00" departLane="-31992229#1_0" departPos="5.10" departSpeed="0.00" departDelay="0.00" arrival="86.00" arrivalLane="-25536089#2_0" arrivalPos="39.53" arrivalSpeed="7.36" duration="54.00" routeLength="324.70" waitingTime="0.00" waitingCount="0" stopTime="0.00" timeLoss="10.43" rerouteNo="0" devices="vehroute_16 tripinfo_16 emissions_16" vType="DEFAULT_VEHTYPE" speedFactor="0.93" vaporized="">
        <emissions CO_abs="2802.747648" CO2_abs="112044.275441" HC_abs="15.352180" PMx_abs="1.984486" NOx_abs="46.698161" fuel_abs="48.163868" electricity_abs="0"/>
    </tripinfo>
    <tripinfo id="21" depart="42.00" departLane="32758219#1_0" departPos="5.10" departSpeed="0.00" departDelay="0.00" arrival="99.00" arrivalLane="449556613#4_0" arrivalPos="13.03" arrivalSpeed="9.57" duration="57.00" routeLength="386.57" waitingTime="0.00" waitingCount="0" stopTime="0.00" timeLoss="10.88" rerouteNo="1" devices="vehroute_21 tripinfo_21 emissions_21" vType="DEFAULT_VEHTYPE" speedFactor="1.02" vaporized="">
        <emissions CO_abs="3213.241046" CO2_abs="144828.587354" HC_abs="17.989851" PMx_abs="2.547685" NOx_abs="60.148080" fuel_abs="62.256370" electricity_abs="0"/>
    </tripinfo>
    <tripinfo id="6" depart="12.00" departLane="317219091#2_0" departPos="5.10" departSpeed="0.00" departDelay="0.00" arrival="112.00" arrivalLane="7421646#2_0" arrivalPos="345.85" arrivalSpeed="14.48" duration="100.00" routeLength="989.65" waitingTime="0.00" waitingCount="0" stopTime="0.00" timeLoss="9.39" rerouteNo="0" devices="vehroute_6 tripinfo_6 emissions_6" vType="DEFAULT_VEHTYPE" speedFactor="1.05" vaporized="">
        <emissions CO_abs="3363.430633" CO2_abs="217825.124010" HC_abs="20.323826" PMx_abs="3.317783" NOx_abs="85.447486" fuel_abs="93.634542" electricity_abs="0"/>
    </tripinfo>
    <tripinfo id="27" depart="54.00" departLane="13866342#0_0" departPos="5.10" departSpeed="0.00" departDelay="0.00" arrival="134.00" arrivalLane="228373543#4_1" arrivalPos="6.70" arrivalSpeed="6.86" duration="80.00" routeLength="648.16" waitingTime="5.00" waitingCount="1" stopTime="0.00" timeLoss="19.79" rerouteNo="0" devices="vehroute_27 tripinfo_27 emissions_27" vType="DEFAULT_VEHTYPE" speedFactor="0.92" vaporized="">
        <emissions CO_abs="3973.645691" CO2_abs="203095.203503" HC_abs="22.831765" PMx_abs="3.572095" NOx_abs="83.540773" fuel_abs="87.302629" electricity_abs="0"/>
    </tripinfo>
    <tripinfo id="14" depart="28.00" departLane="-54451008#0_0" departPos="5.10" departSpeed="0.00" departDelay="0.00" arrival="139.00" arrivalLane="-127219365#0_0" arrivalPos="121.01" arrivalSpeed="8.98" duration="111.00" routeLength="863.16" waitingTime="0.00" waitingCount="0" stopTime="0.00" timeLoss="18.33" rerouteNo="1" devices="vehroute_14 tripinfo_14 emissions_14" vType="DEFAULT_VEHTYPE" speedFactor="1.12" vaporized="">
        <emissions CO_abs="4272.208011" CO2_abs="215765.011151" HC_abs="24.413081" PMx_abs="3.459799" NOx_abs="87.085641" fuel_abs="92.749384" electricity_abs="0"/>
    </tripinfo>
    <tripinfo id="50" depart="100.00" departLane="-75450419#0_0" departPos="5.10" departSpeed="0.00" departDelay="0.00" arrival="144.00" arrivalLane="-129211837#1_0" arrivalPos="12.05" arrivalSpeed="6.37" duration="44.00" routeLength="276.49" waitingTime="0.00" waitingCount="0" stopTime="0.00" timeLoss="6.18" rerouteNo="0" devices="vehroute_50 tripinfo_50 emissions_50" vType="DEFAULT_VEHTYPE" speedFactor="0.90" vaporized="">
        <emissions CO_abs="1990.702498" CO2_abs="81624.477406" HC_abs="10.949113" PMx_abs="1.425345" NOx_abs="33.882241" fuel_abs="35.087462" electricity_abs="0"/>
    </tripinfo>
    <tripinfo id="44" depart="88.00" departLane="-31992222_0" departPos="5.10" departSpeed="0.00" departDelay="0.00" arrival="164.00" arrivalLane="-317101094#10_1" arrivalPos="14.47" arrivalSpeed="8.16" duration="76.00" routeLength="544.28" waitingTime="13.00" waitingCount="1" stopTime="0.00" timeLoss="27.73" rerouteNo="0" devices="vehroute_44 tripinfo_44 emissions_44" vType="DEFAULT_VEHTYPE" speedFactor="1.04" vaporized="">
        <emissions CO_abs="4021.581249" CO2_abs="169752.742451" HC_abs="22.268948" PMx_abs="3.140158" NOx_abs="70.619237" fuel_abs="72.970400" electricity_abs="0"/>
    </tripinfo>
    <tripinfo id="0" depart="0.00" departLane="32665358#1_0" departPos="5.10" departSpeed="0.00" departDelay="0.00" arrival="173.00" arrivalLane="-30999840#1_0" arrivalPos="57.59" arrivalSpeed="7.86" duration="173.00" routeLength="1261.46" waitingTime="0.00" waitingCount="0" stopTime="0.00" timeLoss="30.95" rerouteNo="1" devices="vehroute_0 tripinfo_0 emissions_0" vType="DEFAULT_VEHTYPE" speedFactor="1.06" vaporized="">
        <emissions CO_abs="8113.760671" CO2_abs="381680.837390" HC_abs="45.779863" PMx_abs="6.544233" NOx_abs="157.072501" fuel_abs="164.070250" electricity_abs="0"/>
    </tripinfo>
    <tripinfo id="26" depart="52.00" departLane="-22962976#0_0" departPos="5.10" departSpeed="0.00" departDelay="0.00" arrival="184.00" arrivalLane="24687121#3_0" arrivalPos="65.49" arrivalSpeed="6.96" duration="132.00" routeLength="676.97" waitingTime="23.00" waitingCount="1" stopTime="0.00" timeLoss="37.33" rerouteNo="0" devices="vehroute_26 tripinfo_26 emissions_26" vType="DEFAULT_VEHTYPE" speedFactor="0.87" vaporized="">
        <emissions CO_abs="7278.915479" CO2_abs="221919.677857" HC_abs="38.223956" PMx_abs="3.926211" NOx_abs="92.232173" fuel_abs="95.396924" electricity_abs="0"/>
    </tripinfo>
    <tripinfo id="43" depart="86.00" departLane="317027065#1_0" departPos="5.10" departSpeed="0.00" departDelay="0.00" arrival="186.00" arrivalLane="-129211797#1_0" arrivalPos="69.62" arrivalSpeed="8.19" duration="100.00" routeLength="644.56" waitingTime="25.00" waitingCount="1" stopTime="0.00" timeLoss="39.60" rerouteNo="0" devices="vehroute_43 tripinfo_43 emissions_43" vType="DEFAULT_VEHTYPE" speedFactor="1.09" vaporized="">
        <emissions CO_abs="6325.024874" CO2_abs="233881.375629" HC_abs="34.268651" PMx_abs="4.466641" NOx_abs="98.309704" fuel_abs="100.537367" electricity_abs="0"/>
    </tripinfo>
    <tripinfo id="11" depart="22.00" departLane="-51561196#1_0" departPos="5.10" departSpeed="0.00" departDelay="0.00" arrival="196.00" arrivalLane="32665358#1_0" arrivalPos="16.18" arrivalSpeed="8.75" duration="174.00" routeLength="1368.76" waitingTime="18.00" waitingCount="1" stopTime="0.00" timeLoss="38.96" rerouteNo="1" devices="vehroute_11 tripinfo_11 emissions_11" vType="DEFAULT_VEHTYPE" speedFactor="1.09" vaporized="">
        <emissions CO_abs="8029.349007" CO2_abs="372515.565353" HC_abs="45.124040" PMx_abs="6.172229" NOx_abs="150.460442" fuel_abs="160.131011" electricity_abs="0"/>
    </tripinfo>
    <tripinfo id="56" depart="112.00" departLane="-14039614_0" departPos="5.10" departSpeed="0.00" departDelay="0.00" arrival="203.00" arrivalLane="43321718#1_0" arrivalPos="8.52" arrivalSpeed="5.44" duration="91.00" routeLength="607.24" waitingTime="5.00" waitingCount="1" stopTime="0.00" timeLoss="22.47" rerouteNo="0" devices="vehroute_56 tripinfo_56 emissions_56" vType="DEFAULT_VEHTYPE" speedFactor="1.10" vaporized="">
        <emissions CO_abs="4154.115143" CO2_abs="189512.817389" HC_abs="23.291719" PMx_abs="3.218698" NOx_abs="77.824326" fuel_abs="81.464590" electricity_abs="0"/>
    </tripinfo>
    <tripinfo id="71" depart="142.00" departLane="-129211821#7_0" departPos="5.10" departSpeed="0.00" departDelay="0.00" arrival="212.00" arrivalLane="125880830#0_0" arrivalPos="61.53" arrivalSpeed="13.84" duration="70.00" routeLength="604.62" waitingTime="0.00" waitingCount="0" stopTime="0.00" timeLoss="11.33" rerouteNo="0" devices="vehroute_71 tripinfo_71 emissions_71" vType="DEFAULT_VEHTYPE" speedFactor="1.04" vaporized="">
        <emissions CO_abs="3460.445716" CO2_abs="189258.566203" HC_abs="20.170271" PMx_abs="3.283631" NOx_abs="77.595925" fuel_abs="81.354661" electricity_abs="0"/>
    </tripinfo>
    <tripinfo id="49" depart="98.00" departLane="317544588#0_0" departPos="5.10" departSpeed="0.00" departDelay="0.00" arrival="213.00" arrivalLane="25536089#1_0" arrivalPos="24.56" arrivalSpeed="8.20" duration="115.00" routeLength="813.42" waitingTime="0.00" waitingCount="0" stopTime="0.00" timeLoss="15.44" rerouteNo="1" devices="vehroute_49 tripinfo_49 emissions_49" vType="DEFAULT_VEHTYPE" speedFactor="1.00" vaporized="">
        <emissions CO_abs="4712.110577" CO2_abs="216149.689145" HC_abs="26.410010" PMx_abs="3.478771" NOx_abs="87.605307" fuel_abs="92.915064" electricity_abs="0"/>
    </tripinfo>
    <tripinfo id="1" depart="2.00" departLane="450023077#0_0" departPos="5.10" departSpeed="0.00" departDelay="0.00" arrival="215.00" arrivalLane="43321719#1_0" arrivalPos="28.51" arrivalSpeed="6.55" duration="213.00" routeLength="834.17" waitingTime="91.00" waitingCount="3" stopTime="0.00" timeLoss="119.49" rerouteNo="0" devices="vehroute_1 tripinfo_1 emissions_1" vType="DEFAULT_VEHTYPE" speedFactor="0.94" vaporized="">
        <emissions CO_abs="17835.284879" CO2_abs="443120.079750" HC_abs="91.566967" PMx_abs="9.374020" NOx_abs="192.980875" fuel_abs="190.485247" electricity_abs="0"/>
    </tripinfo>
    <tripinfo id="2" depart="4.00" departLane="-317003246_0" departPos="5.10" departSpeed="0.00" departDelay="0.00" arrival="218.00" arrivalLane="-52241898#0_0" arrivalPos="31.36" arrivalSpeed="7.77" duration="214.00" routeLength="801.97" waitingTime="116.00" waitingCount="4" stopTime="0.00" timeLoss="146.07" rerouteNo="0" devices="vehroute_2 tripinfo_2 emissions_2" vType="DEFAULT_VEHTYPE" speedFactor="1.01" vaporized="">
        <emissions CO_abs="21074.783016" CO2_abs="520402.331587" HC_abs="108.197585" PMx_abs="11.384678" NOx_abs="228.248191" fuel_abs="223.706401" electricity_abs="0"/>
    </tripinfo>
    <tripinfo id="18" depart="36.00" departLane="-22962977#1_0" departPos="5.10" departSpeed="0.00" departDelay="0.00" arrival="235.00" arrivalLane="129211855_0" arrivalPos="39.02" arrivalSpeed="6.98" duration="199.00" routeLength="1196.71" waitingTime="45.00" waitingCount="1" stopTime="0.00" timeLoss="65.75" rerouteNo="1" devices="vehroute_18 tripinfo_18 emissions_18" vType="DEFAULT_VEHTYPE" speedFactor="0.94" vaporized="">
        <emissions CO_abs="12744.771556" CO2_abs="413927.377081" HC_abs="67.643086" PMx_abs="7.810006" NOx_abs="174.105131" fuel_abs="177.934200" electricity_abs="0"/>
    </tripinfo>
</tripinfos>
